image_empty_space_cropper/main.py
image_empty_space_cropper-0.1.2.dist-info/entry_points.txt
image_empty_space_cropper-0.1.2.dist-info/WHEEL
image_empty_space_cropper-0.1.2.dist-info/METADATA
image_empty_space_cropper-0.1.2.dist-info/RECORD
